setup.cfg
setup.py
ReenigneAgent.egg-info/PKG-INFO
ReenigneAgent.egg-info/SOURCES.txt
ReenigneAgent.egg-info/dependency_links.txt
ReenigneAgent.egg-info/entry_points.txt
ReenigneAgent.egg-info/requires.txt
ReenigneAgent.egg-info/top_level.txt
ragent/__init__.py
ragent/agent.py
ragent/module.py
ragent/modules/__init__.py
ragent/modules/cpu.py
ragent/modules/loadavg.py
ragent/modules/memory.py
ragent/modules/network.py
ragent/utils/__init__.py
ragent/utils/api.py
ragent/utils/config.py