Metadata-Version: 1.0
Name: ReenigneAgent
Version: 0.1
Summary: Reenigne Monitoring Agent
Home-page: https://monitor.reenigne.net
Author: Matt Vandermeulen, Reenigne
Author-email: UNKNOWN
License: UNKNOWN
Platform: UNKNOWN
